{"user_name":"Florent","user_username":"florent","user_bio":"IT Business Analyst for 8+ years, I am finding joy in developping again, with the help of n8n and AIs 🤗","user_links":"","user_avatar":"https://gravatar.com/avatar/0ee3705eecc1ae4bcf7711dffac52a361d8a770574abbacab758008a85f440b6?r=pg&d=retro&size=200","url":"https://n8nworkflows.xyz/workflows/restore-workflows-and-credentials-from-remote-ftp-backup-storage-9156\n","url_n8n":"https://n8n.io/workflows/9156","nodeTypes":{"n8n-nodes-base.if":{"count":2},"n8n-nodes-base.ftp":{"count":5},"n8n-nodes-base.code":{"count":2},"n8n-nodes-base.filter":{"count":1},"n8n-nodes-base.emailSend":{"count":2},"n8n-nodes-base.stickyNote":{"count":3},"n8n-nodes-base.stopAndError":{"count":1},"n8n-nodes-base.manualTrigger":{"count":1},"n8n-nodes-base.readWriteFile":{"count":2},"n8n-nodes-base.executeCommand":{"count":4}},"categories":[{"id":31,"name":"Content Creation"},{"id":51,"name":"Multimodal AI"}]}