{"user_name":"Bastien Laval","user_username":"bastien-laval","user_bio":"","user_links":"","user_avatar":"https://gravatar.com/avatar/d7c42e46c2daf4cf90ac38772f9eee0be4bb2883bd5cf161158fff01be2b1d5e?r=pg&d=retro&size=200","url":"https://n8nworkflows.xyz/workflows/reschedule-overdue-asana-tasks-and-clean-up-completed-tasks-2701\n","url_n8n":"https://n8n.io/workflows/2701","nodeTypes":{"n8n-nodes-base.if":{"count":2},"n8n-nodes-base.asana":{"count":4},"n8n-nodes-base.stickyNote":{"count":3},"n8n-nodes-base.scheduleTrigger":{"count":1}},"categories":[{"id":2,"name":"Sales"},{"id":17,"name":"HR"},{"id":18,"name":"Product"}]}