{"user_name":"Dhruv Dalsaniya","user_username":"ddm21","user_bio":"IT Professional & Freelance Automation Consultant specializing in AI-driven automation and business process optimization","user_links":"https://in.linkedin.com/in/dhruvdalsaniya21","user_avatar":"https://gravatar.com/avatar/367111bb2fd90204e1ce6f05ef666d8e9e6b73829748584483278f1843c02060?r=pg&d=retro&size=200","url":"https://n8nworkflows.xyz/workflows/midjourney-image-generator-via-telegram-and-goapi-5097\n","url_n8n":"https://n8n.io/workflows/5097","nodeTypes":{"n8n-nodes-base.if":{"count":3},"n8n-nodes-base.set":{"count":1},"n8n-nodes-base.wait":{"count":2},"n8n-nodes-base.discord":{"count":1},"n8n-nodes-base.telegram":{"count":4},"n8n-nodes-base.stickyNote":{"count":2},"n8n-nodes-base.httpRequest":{"count":4},"n8n-nodes-base.telegramTrigger":{"count":1}},"categories":[{"id":25,"name":"AI"}]}