{"user_name":"Club de Inteligencia Artificial Politécnico CIAP","user_username":"ciap","user_bio":"","user_links":"","user_avatar":"https://gravatar.com/avatar/db11ab33fddf6c5bd0765bf4954262a3c6ce53d3652ffc9b9a8d1b442146fcf0?r=pg&d=retro&size=200","url":"https://n8nworkflows.xyz/workflows/telegram-appointment-scheduler-bot-with-google-calendar---sheets-8809\n","url_n8n":"https://n8n.io/workflows/8809","nodeTypes":{"n8n-nodes-base.if":{"count":3},"n8n-nodes-base.code":{"count":4},"n8n-nodes-base.switch":{"count":1},"n8n-nodes-base.telegram":{"count":8},"n8n-nodes-base.stickyNote":{"count":7},"n8n-nodes-base.googleSheets":{"count":4},"n8n-nodes-base.googleCalendar":{"count":4},"n8n-nodes-base.telegramTrigger":{"count":1}},"categories":[{"id":40,"name":"Support Chatbot"},{"id":47,"name":"AI Chatbot"}]}