{"user_name":"WeblineIndia","user_username":"weblineindia","user_bio":"A Leading Software Engineering, Consulting & Outsourcing Services Company in USA & India serving Clients Globally since 1999.","user_links":"https://www.weblineindia.com/","user_avatar":"https://gravatar.com/avatar/a229d43aefca4588581583c58bb37b4773aebbdf4c1fef86a08bb1d38eae91fa?r=pg&d=retro&size=200","url":"https://n8nworkflows.xyz/workflows/generate-weekly-energy-consumption-reports-with-energidataservice--email-and-google-drive-7592\n","url_n8n":"https://n8n.io/workflows/7592","nodeTypes":{"n8n-nodes-base.code":{"count":1},"n8n-nodes-base.cron":{"count":1},"n8n-nodes-base.emailSend":{"count":1},"n8n-nodes-base.stickyNote":{"count":6},"n8n-nodes-base.googleDrive":{"count":1},"n8n-nodes-base.httpRequest":{"count":1},"n8n-nodes-base.convertToFile":{"count":1}},"categories":[{"id":35,"name":"Document Extraction"},{"id":51,"name":"Multimodal AI"}]}